WebReg/__init__.py
WebReg/_exceptions.py
WebReg/_operation.py
WebReg/_study_list.py
WebReg/_utils.py
webreg-0.2.dist-info/LICENSE
webreg-0.2.dist-info/METADATA
webreg-0.2.dist-info/WHEEL
webreg-0.2.dist-info/top_level.txt
webreg-0.2.dist-info/RECORD
