Metadata-Version: 2.1
Name: webreg
Version: 0.2
Summary: Python API for UCI WebReg
Home-page: https://github.com/maao666/UCI_WebReg_API
Author: Mason
Author-email: maao666@icloud.com
License: Apache License
Download-URL: https://github.com/maao666/UCI_WebReg_API/archive/v0.2.tar.gz
Keywords: UCI,UC Irvine,WebReg,API,bot,enrollment
Platform: UNKNOWN
Classifier: Programming Language :: Python :: 3
Classifier: License :: OSI Approved :: MIT License
Classifier: Operating System :: OS Independent
Requires-Python: >=3.6
Requires-Dist: selenium
Requires-Dist: beautifulsoup4
